site_utils/__init__.py
site_utils/admin.py
site_utils/apps.py
site_utils/cleanup.py
site_utils/context_processors.py
site_utils/defaults.py
site_utils/handlers.py
site_utils/models.py
site_utils/notify.py
site_utils/patches.py
site_utils/settings.py
site_utils/signals.py
site_utils/urls.py
site_utils/utils.py
site_utils/views.py
site_utils/management/__init__.py
site_utils/management/commands/__init__.py
site_utils/management/commands/site_cleanup.py
site_utils/management/commands/site_config.py
site_utils/management/commands/site_error_page.py
site_utils/management/commands/site_notify.py
site_utils/management/commands/site_update.py
site_utils/templates/site_utils/error.html
site_utils/templates/site_utils/notify_body.txt
site_utils/templates/site_utils/notify_subject.txt
Django_Site_Utils-0.3.7.dist-info/LICENSE
Django_Site_Utils-0.3.7.dist-info/METADATA
Django_Site_Utils-0.3.7.dist-info/WHEEL
Django_Site_Utils-0.3.7.dist-info/top_level.txt
Django_Site_Utils-0.3.7.dist-info/RECORD
