Metadata-Version: 2.1
Name: Django-Site-Utils
Version: 0.3.7
Summary: Django site-wide management commands and utilities.
Home-page: https://github.com/ninemoreminutes/django-site-utils/
Author: Nine More Minutes, Inc.
Author-email: projects@ninemoreminutes.com
License: BSD
Project-URL: Documentation, https://django-site-utils.rtfd.org/
Project-URL: Source, https://github.com/ninemoreminutes/django-site-utils/
Project-URL: Tracker, https://github.com/ninemoreminutes/django-site-utils/issues
Keywords: django,site,management
Platform: UNKNOWN
Classifier: Development Status :: 3 - Alpha
Classifier: Environment :: Web Environment
Classifier: Framework :: Django
Classifier: Framework :: Django :: 1.11
Classifier: Framework :: Django :: 2.0
Classifier: Framework :: Django :: 2.1
Classifier: Framework :: Django :: 2.2
Classifier: Framework :: Django :: 3.0
Classifier: Framework :: Django :: 3.1
Classifier: Framework :: Django :: 3.2
Classifier: Intended Audience :: Developers
Classifier: License :: OSI Approved :: BSD License
Classifier: Operating System :: OS Independent
Classifier: Programming Language :: Python
Classifier: Programming Language :: Python :: 3
Classifier: Programming Language :: Python :: 3.5
Classifier: Programming Language :: Python :: 3.6
Classifier: Programming Language :: Python :: 3.7
Classifier: Programming Language :: Python :: 3.8
Classifier: Programming Language :: Python :: 3.9
Classifier: Topic :: Internet :: WWW/HTTP
Classifier: Topic :: Software Development :: Libraries
Classifier: Topic :: Software Development :: Libraries :: Python Modules
Requires-Dist: django (>=1.11)
Requires-Dist: six
